teststs/__init__.py
teststs-1.1.0.dist-info/licenses/LICENSE
teststs-1.1.0.dist-info/METADATA
teststs-1.1.0.dist-info/WHEEL
teststs-1.1.0.dist-info/top_level.txt
teststs-1.1.0.dist-info/RECORD
